[
  { "id": 0, "name": "salade", 
    "category": {
      "value": "starter"
    }
  },
  { "id": 3, "name": "tapenade",
    "category":{
      "value": "starter"
    }
  },
  { "id": 6, "name": "tacos",
    "category": {
      "value":"main-course"
    }
  },
  { "id": 9, "name": "mousse au chocolat",
    "category": {
      "value": "dessert"
    }
  },
  { "id": 1, "name": "oeufs mimosa",
    "category": {
      "value": "starter"
    }
  },
  { "id": 8, "name": "tarte",
    "category": {
      "value": "dessert"
    }
  },
  { "id": 2, "name": "gaspacio",
    "category": {
      "value": "starter"
      }
  },
  { "id": 5, "name": "kebab",
    "category": {
      "value": "main-course"
      }
  },
  { "id": 7, "name": "purée de pattate",
    "category": {
      "value": "main-course"
      }
  },
  { "id": 10, "name": "croissant",
    "category": {
      "value": "dessert"
    }
  },
  { "id": 11, "name": "bounty",
    "category": {
      "value": "dessert"
    }
  },
  { "id" :4, "name": "steak",
    "category": {
      "value": "main-course"
    }
  }
]
